{
    "refresh": "",
    "more": "",
    "data": [
        {
            "id": "1",
            "title": "李秋平回归首训：着手改造上海队，尊重刘炜决定",
            "image": "/10007/20180525/cba/李秋平回归首训：着手改造上海队，尊重刘炜决定.jpg",
            "time": "2018 05 25 00:00:00",
            "content": "/10007/20180525/cba/李秋平回归首训：着手改造上海队，尊重刘炜决定.html"
        },
        {
            "id": "2",
            "title": "李秋平：想念本帮菜，希望把球队打造成上海名片",
            "image": "/10007/20180525/cba/李秋平：想念本帮菜，希望把球队打造成上海名片.jpg",
            "time": "2018 05 25 00:00:00",
            "content": "/10007/20180525/cba/李秋平：想念本帮菜，希望把球队打造成上海名片.html"
        },
        {
            "id": "3",
            "title": "四川队官宣：前德国队主帅鲍曼将任球队主教练",
            "image": "/10007/20180525/cba/四川队官宣：前德国队主帅鲍曼将任球队主教练.jpg",
            "time": "2018 05 25 00:00:00",
            "content": "/10007/20180525/cba/四川队官宣：前德国队主帅鲍曼将任球队主教练.html"
        },
        {
            "id": "4",
            "title": "哈达迪接受采访：我在任何球队都打得努力强硬",
            "image": "/10007/20180525/cba/哈达迪接受采访：我在任何球队都打得努力强硬.jpg",
            "time": "2018 05 25 00:00:00",
            "content": "/10007/20180525/cba/哈达迪接受采访：我在任何球队都打得努力强硬.html"
        },
        {
            "id": "5",
            "title": "赵岩昊晒特训生活：全身酸痛但十分满足",
            "image": "/10007/20180525/cba/赵岩昊晒特训生活：全身酸痛但十分满足.jpg",
            "time": "2018 05 25 00:00:00",
            "content": "/10007/20180525/cba/赵岩昊晒特训生活：全身酸痛但十分满足.html"
        }
    ]
}